youtube_video_analyzer/__init__.py
youtube_video_analyzer/face_detection.py
youtube_video_analyzer/frame_extract.py
youtube_video_analyzer/sound_extract.py
youtube_video_analyzer/sound_intervals.py
youtube_video_analyzer/video_downloader.py
youtube_video_analyzer-0.3.4.dist-info/METADATA
youtube_video_analyzer-0.3.4.dist-info/WHEEL
youtube_video_analyzer-0.3.4.dist-info/top_level.txt
youtube_video_analyzer-0.3.4.dist-info/RECORD
