Metadata-Version: 2.1
Name: youtube_video_analyzer
Version: 0.3.4
Summary: A package for downloading YouTube videos, extracting audio and frames, and analyzing sound intervals
Home-page: https://github.com/Cornelius-BobCat/package-video-downloader
Author: Cornelius Vincent
Author-email: pro.cornelius@gmail.com
Classifier: Programming Language :: Python :: 3
Classifier: License :: OSI Approved :: MIT License
Classifier: Operating System :: OS Independent
Requires-Python: >=3.6
Requires-Dist: pytube
Requires-Dist: moviepy
Requires-Dist: librosa
Requires-Dist: imageio
Requires-Dist: numpy
Requires-Dist: opencv-python
